{
    "company_overview": {
        "name": "TekRevol",
        "description": "TekRevol is a technology and mobile app development company that offers cutting-edge digital solutions to clients worldwide. Established with the aim of providing innovative, scalable, and reliable solutions, TekRevol has rapidly grown to become a global leader in the tech industry. They specialize in mobile app development, web development, enterprise solutions, and digital marketing services."
    },
    "founding_and_history": {
        "year_established": 2018,
        "founders": [
            "Abeer Raza",
            "Waqas Naeem",
            "Nabeel Rehman"
        ],
        "headquarters": "Silicon Valley, California, USA",
        "history": "TekRevol started as a small startup with a vision to revolutionize the technology and app development landscape. Since its inception in 2018, the company has expanded its operations to multiple regions, including the United States, the United Arab Emirates, and Pakistan. The founders had a clear goal of creating user-friendly and cutting-edge digital solutions, which led to rapid growth and an impressive client portfolio."
    },
    "core_services": {
        "mobile_app_development": {
            "iOS_App_Development": "Building native and hybrid apps for iPhone and iPad with a focus on user experience and performance.",
            "Android_App_Development": "Creating innovative, scalable, and secure Android applications for various industries.",
            "Cross-Platform_App_Development": "Using frameworks like React Native and Flutter to develop apps that work seamlessly across different platforms."
        },
        "web_development": {
            "Custom_Website_Development": "Tailoring websites according to clients’ specific business needs and goals.",
            "E-Commerce_Development": "Developing high-performing, user-friendly, and secure e-commerce websites using platforms like Shopify, WooCommerce, and Magento.",
            "Content_Management_Systems": "Creating easy-to-manage websites with CMS platforms like WordPress, Joomla, and Drupal."
        },
        "enterprise_solutions": {
            "ERP_and_CRM_Solutions": "Developing enterprise-grade ERP and CRM solutions that streamline business operations and improve efficiency.",
            "Cloud_Solutions": "Implementing cloud-based solutions using AWS, Google Cloud, and Microsoft Azure to enhance data accessibility and security."
        },
        "digital_marketing": {
            "Search_Engine_Optimization": "Providing SEO services to improve website visibility and organic search rankings.",
            "Social_Media_Marketing": "Managing social media campaigns to build brand awareness and engagement.",
            "Content_Marketing": "Creating high-quality content strategies that drive traffic and generate leads."
        }
    },
    "industries_served": [
        "Healthcare",
        "Education",
        "Finance",
        "E-Commerce",
        "Real Estate",
        "Entertainment"
    ],
    "key_achievements_and_awards": [
        {
            "award": "Top Mobile App Development Company",
            "recognized_by": [
                "Clutch",
                "GoodFirms",
                "AppFutura"
            ],
            "description": "Recognized as one of the top mobile app development companies globally."
        },
        {
            "award": "Best Enterprise App Developer",
            "awarded_by": "TopDevelopers",
            "year": 2021,
            "description": "Awarded for delivering high-quality enterprise solutions."
        },
        {
            "award": "Fastest Growing Company",
            "listed_by": "INC 5000",
            "year": 2020,
            "description": "Listed among the fastest-growing tech companies."
        }
    ],
    "notable_projects_and_case_studies": [
        {
            "project_name": "MediQure App",
            "industry": "Healthcare",
            "description": "Developed a telemedicine app that connects patients with doctors through video consultations, appointment scheduling, and prescription management.",
            "impact": "Helped reduce wait times for patients and improved access to healthcare services, especially during the pandemic."
        },
        {
            "project_name": "EduLearn Platform",
            "industry": "Education",
            "description": "Created an e-learning platform with video tutorials, quizzes, and interactive content, enabling students to learn remotely.",
            "impact": "The platform saw a 300% increase in student engagement and became a popular tool for remote education."
        },
        {
            "project_name": "ShopEase E-Commerce App",
            "industry": "Retail",
            "description": "Developed a cross-platform e-commerce app that allows users to browse, purchase, and track orders seamlessly.",
            "impact": "Helped the client increase sales by 150% within six months of launch."
        }
    ],
    "technology_stack": {
        "mobile_development": [
            "Swift",
            "Kotlin",
            "React Native",
            "Flutter"
        ],
        "web_development": [
            "JavaScript",
            "Angular",
            "React",
            "Vue.js",
            "Node.js"
        ],
        "backend_development": [
            "PHP",
            "Python",
            "Java",
            ".NET"
        ],
        "database_management": [
            "MySQL",
            "PostgreSQL",
            "MongoDB"
        ],
        "cloud_services": [
            "AWS",
            "Microsoft Azure",
            "Google Cloud"
        ],
        "devops": [
            "Docker",
            "Kubernetes",
            "Jenkins"
        ]
    },
    "company_culture_and_values": [
        "Innovation",
        "Client-Centricity",
        "Quality",
        "Collaboration",
        "Continuous Learning"
    ],
    "global_presence": {
        "United_States": [
            "Headquarters in Silicon Valley",
            "Additional offices in Houston and New York"
        ],
        "United_Arab_Emirates": [
            "Dubai office serving the Middle Eastern market"
        ],
        "Pakistan": [
            "Development centers in Karachi and Lahore"
        ]
    },
    "leadership_team": [
        {
            "name": "Abeer Raza",
            "position": "Co-Founder & CMO",
            "role": "Leading the marketing strategies and helping the company reach global audiences."
        },
        {
            "name": "Waqas Naeem",
            "position": "Co-Founder & COO",
            "role": "Responsible for operations, project management, and ensuring efficient service delivery."
        },
        {
            "name": "Nabeel Rehman",
            "position": "Co-Founder & CEO",
            "role": "Spearheading the company's vision, strategy, and growth."
        }
    ],
    "contact_information": {
        "website": "www.tekrevol.com",
        "email": "info@tekrevol.com",
        "phone": "+1 (800) 362-9239",
        "address": "2100 Geng Road, Suite 210, Palo Alto, CA 94303"
    },
    "faqs": [
        {
            "question": "What industries does TekRevol serve?",
            "answer": "TekRevol serves industries like healthcare, education, finance, e-commerce, real estate, and entertainment."
        },
        {
            "question": "What services does TekRevol offer?",
            "answer": "TekRevol offers services such as mobile app development, web development, enterprise solutions, and digital marketing."
        },
        {
            "question": "Where is TekRevol located?",
            "answer": "TekRevol’s headquarters is in Silicon Valley, California, with additional offices in the USA, UAE, and Pakistan."
        }
    ]
}